odoo/addons/l10n_br_crm/README.rst
odoo/addons/l10n_br_crm/__init__.py
odoo/addons/l10n_br_crm/__manifest__.py
odoo/addons/l10n_br_crm/i18n/l10n_br_crm.pot
odoo/addons/l10n_br_crm/i18n/pt_BR.po
odoo/addons/l10n_br_crm/models/__init__.py
odoo/addons/l10n_br_crm/models/crm_lead.py
odoo/addons/l10n_br_crm/readme/CONFIGURE.rst
odoo/addons/l10n_br_crm/readme/CONTRIBUTORS.rst
odoo/addons/l10n_br_crm/readme/DESCRIPTION.rst
odoo/addons/l10n_br_crm/readme/INSTALL.rst
odoo/addons/l10n_br_crm/readme/ROADMAP.rst
odoo/addons/l10n_br_crm/readme/USAGE.rst
odoo/addons/l10n_br_crm/static/description/icon.png
odoo/addons/l10n_br_crm/static/description/index.html
odoo/addons/l10n_br_crm/tests/__init__.py
odoo/addons/l10n_br_crm/tests/test_crm_lead.py
odoo/addons/l10n_br_crm/tests/test_crm_onchange.py
odoo/addons/l10n_br_crm/views/crm_lead_view.xml
odoo/addons/l10n_br_crm/views/crm_quick_create_opportunity_form.xml
odoo14_addon_l10n_br_crm-14.0.1.3.1.dist-info/METADATA
odoo14_addon_l10n_br_crm-14.0.1.3.1.dist-info/WHEEL
odoo14_addon_l10n_br_crm-14.0.1.3.1.dist-info/top_level.txt
odoo14_addon_l10n_br_crm-14.0.1.3.1.dist-info/RECORD
